{
	"Circles": [{
		"name": "circle",
		"radius": 50,
		"cx": 80,
		"cy": 10,
		"fill": "green"

	},
	{
	"name": "circle1",
		"radius": 150,
		"cx": 500,
		"cy": 50,
		"fill": "teal"
		},
		{
		"name": "circle2",
		"radius": 100,
		"cx": 200,
		"cy": 150,
		"fill": "lawngreen"
		}],
		
		
	
	

	"Rectangle": [{
		"name": "rect",
		"x": 50,
		"y": -250,
		"height": 100,
		"width": 130,
		"fill": "red"
	},
	{
		"name": "rect1",
		"x": 150,
		"y": -600,
		"height": 190,
		"width": 220,
		"fill": "lime"
	
	
	
	},
	{
	"name": "rect2",
		"x": 600,
		"y": -500,
		"height": 300,
		"width": 500,
		"fill": "maroon"
	
	}],
	
	"Lines": [{
		"name": "line",
		"x1": 30,
		"y1": 80,
		"x2": 80,
		"y2": 80,
		"stroke": "orange",
		"stroke-width": 8
	},
	{
		"name": "line1",
		"x1": 5,
		"y1": 280,
		"x2": 2,
		"y2": 5,
		"stroke": "yellow",
		"stroke-width": 9
	
	},
	
	{"name": "line2",
		"x1": 92,
		"y1": 92,
		"x2": 40,
		"y2": 80,
		"stroke": "indigo",
		"stroke-width": 6
	
	
	}	],

	"Polygons": [{
			"name": "polygon 1",
			"points": [{
					"x": 341.0,
					"y": 203.0
				},
				{
					"x": 531.0,
					"y": 230.4
				},
				{
					"x": 481.0,
					"y": 318.0
				},
				{
					"x": 117.0,
					"y": 323.5
				}
			]
		},
		{
			"name": "polygon 2",
			"points": [{
					"x": 0.0,
					"y": 50.0
				},
				{
					"x": 15.5,
					"y": 23.4
				},
				{
					"x": 18.0,
					"y": 30.0
				},
				{
					"x": 20.0,
					"y": 16.5
				}
			]
		},
		{
		
		 "name": "polygon 3",
			"points": [{
					"x": 22.0,
					"y": 10.0
				},
				{
					"x": 30.0,
					"y": 21.0
				},
				{
					"x": 17.0,
					"y": 25.0
				},
				{
					"x": 12.0,
					"y": 23.5
				}
		]
},

{
"name": "polygon 4",
			"points": [{
					"x": 200.0,
					"y": 10.0
				},
				{
					"x": 40.0,
					"y": 20.0
				},
				{
					"x": 19.0,
					"y": 8.0
				},
				{
					"x": 10.0,
					"y": 23.0
				},
				{
				"x":16.0,
				"y": 19.0
				}

]
}
]
}
